{
  "_meta": {
    "project": "n6-architecture",
    "updated": "2026-04-08",
    "strategy": "ossified/stable/failed 수렴 추적"
  },
  "ossified": {
    "_description": "골화 완료 — 불변, 변경 금지",
    "CORE_THEOREM": {
      "status": "PASS",
      "value": "σφ=nτ ⟺ n=6, 3개 독립 증명",
      "threshold": "반례 0 (10^8 탐색)"
    },
    "BT_380": {
      "status": "PASS",
      "value": "380 돌파 정리 (BT-372~380 지질/기상/빙권/해양/대기화학/곡률/워프/추가차원/메타 추가)",
      "threshold": "전수 검증 + atlas 등록",
      "note": "2026-04-08 BT-343 → BT-380 확장, 각 BT n=6 수식 도출 + 검증예측 포함"
    },
    "AI_17_TECHNIQUES": {
      "status": "PASS",
      "value": "17 기법 실험 확정",
      "threshold": "71% FLOPs, 3x FFT, 67% param 등"
    },
    "DSE_322_TOML": {
      "status": "PASS",
      "value": "322 도메인 TOML 정의",
      "threshold": "5,893,032+ 조합 탐색 완료"
    },
    "PRODUCTS_118": {
      "status": "PASS",
      "value": "118/125 제품 🛸10",
      "threshold": "천장 도달"
    },
    "UNIQUENESS_PROOF": {
      "status": "PASS",
      "value": "z=4.02 (큰 수 Monte Carlo)",
      "threshold": "p<0.0001"
    },
    "N28_CONTROL": {
      "status": "PASS",
      "value": "n=28 z=-2.35 (무작위 이하)",
      "threshold": "n=6 유일성 대조 확인"
    },
    "BT_134_PERIODIC_TABLE": {
      "status": "PASS",
      "value": "BT-134 주기열 {2,8,8,18,18,32,32} + Evidence 4 (2^sopfr=32) 교정",
      "threshold": "2200건 산술 정합 스캔 통과",
      "note": "2026-04-08 수정, ~/Dev/nexus/shared/bt-consistency-report.md"
    }
  },
  "stable": {
    "_description": "안정 — 통과했지만 아직 골화 전",
    "PAPERS_39": {
      "status": "PASS",
      "value": "39편 Zenodo DOI 발행",
      "note": "내용 갱신 가능, 신규 추가 중"
    },
    "LENS_2161_TESTS": {
      "status": "PASS",
      "value": "397종 렌즈, causal_chain + faction_debate 포함 cargo test 2161 PASS",
      "threshold": "전체 테스트 100%",
      "note": "2026-04-08 빌드캐시 재생성 후 재확인"
    },
    "PRODUCTS_7_REMAINING": {
      "status": "PASS",
      "value": "7개 잔여 🛸7→10 승격 진행중",
      "note": "바이러스학/곤충학/나노봇 Mk.I~V 완료 (products.json 동기화 확인)"
    },
    "CAUSAL_CHAIN_PAPER": {
      "status": "PASS",
      "value": "인과 사슬 논문 초안 완성",
      "note": "최종 검증 + papers 발행 대기"
    },
    "MONTE_CARLO_V8": {
      "status": "PASS",
      "value": "342노드, 자연 z=959.12 / 로그균등 z=20.19 (p<10^-89), π/e/φ 대조 z=3~10",
      "threshold": "z>5 재현 + 대조군 분리",
      "note": "2026-04-08 docs/reality-map-monte-carlo-v8.md, 큰수 N=10 한계 명시"
    },
    "REALITY_MAP_V8_SYNC": {
      "status": "PASS",
      "value": "atlas.n6 단독 소스 전환 완료 (reality_map JSON 폐기), 342노드 동기화, 엣지 정합성 정리",
      "threshold": "3D 지도 정상 렌더, atlas.n6 파서 기반",
      "note": "2026-04-08 수동 동기화, hexa 자동화는 HEXA_LOCAL_IO 해소 후"
    },
    "ATLAS_REALITY_LINK": {
      "status": "PASS",
      "value": "아틀라스 1876행 ↔ reality_map 342노드 매칭 23.72% / 노드 36.3%",
      "threshold": "교차 매핑 문서화",
      "note": "2026-04-08 docs/atlas-reality-map-link.md, 미커버 218개는 L0~L5 기초 사다리(아틀라스 응용 편향)"
    }
  },
  "failed": {
    "_description": "실패 — 수정 필요, 골화 불가",
    "HEXA_LOCAL_IO": {
      "status": "FAIL",
      "value": "scripts/sync_reality_map.hexa 작성 완료, 실행 차단",
      "threshold": "hexa 로컬 파일시스템 IO 가능",
      "cause": "hexa 인터프리터가 airgenome 원격 게이트(aiden@server)에서 실행 → $HOME/Dev/nexus/shared 미마운트",
      "fix": "hexa 로컬 모드 추가 또는 airgenome에 nexus/shared bind-mount"
    },
    "CROSS_DSE": {
      "status": "FAIL",
      "value": "미실행",
      "threshold": "335 TOML 교차 융합",
      "cause": "개별 DSE만 완료, 교차 재조합 미진행",
      "fix": "universal-dse Cross-DSE 모드 실행"
    },
    "GOAL_MD_MISSING": {
      "status": "PASS",
      "value": "20개 도메인 goal.md 생성 완료 (geology/meteorology/music/ocean/climate/astronomy/neuroscience/network/crystallography/cosmology/ecology/electromagnetism/genetics/immunology/pharmacology/thermodynamics/optics/topology/fluid/plasma)",
      "threshold": "전 도메인 goal.md 존재",
      "note": "2026-04-09 domain_seeds.jsonl 기반 20개 생성, 잔여 49개 hexa-infra/anima 계열은 별도 추적"
    }
  }
}
