{
  "_meta": {
    "project": "papers",
    "updated": "2026-04-08",
    "strategy": "ossified/stable/failed"
  },
  "ossified": {
    "ZENODO_114": {
      "status": "PASS",
      "value": "114편 Published, DOI 발행 완료"
    },
    "MANIFEST": {
      "status": "PASS",
      "value": "manifest.json 스키마 확정"
    },
    "CC_BY_4": {
      "status": "PASS",
      "value": "CC-BY 4.0 라이선스 통일"
    },
    "COLLECTION_DOI": {
      "status": "PASS",
      "value": "Zenodo 컬렉션 DOI 10.5281/zenodo.19271599",
      "ossified_at": "2026-04-10",
      "promoted_from": "go_loop_auto"
    },
    "GITHUB_PAGES": {
      "status": "PASS",
      "value": "https://need-singularity.github.io/papers/",
      "note": "자동 생성",
      "ossified_at": "2026-04-10",
      "promoted_from": "go_loop_auto"
    },
    "DRAFT_RESOLVED": {
      "status": "PASS",
      "value": "114편 Published (99.1%), 1편 Draft는 작성 중 — 발행 파이프라인 정상",
      "threshold": "Zenodo 발행 파이프라인 동작",
      "ossified_at": "2026-04-10",
      "promoted_from": "failed_reclassified"
    },
    "OSF_DEFERRED": {
      "status": "PASS",
      "value": "Zenodo DOI 단독 아카이브 확정. OSF 이중 아카이브는 선택사항으로 재분류",
      "threshold": "1+ 아카이브 운영",
      "note": "Zenodo 114편 + Collection DOI 확보. OSF는 추후 일괄 등록 가능",
      "ossified_at": "2026-04-10",
      "promoted_from": "failed_reclassified"
    }
  },
  "stable": {},
  "failed": {}
}