{"schema_version":"cdg_matrix_verification_v1","timestamp":"2026-04-15T16:43:49Z","task":"CDG-P7-5","input_dir":"/Users/ghost/Dev/nexus/engine/cross_domain","status":"PASS","total_files":4,"total_pairs":96,"expected_pairs_p7_1to4":96,"expected_phase_range":"P1..P112","schema_ok_count":96,"schema_fail_count":0,"schema_fields_required":["phase","pair_id","source_domain","target_domain","analogy","shared_invariant","differentiator","n6_match"],"n6_match_allowed":["EXACT","STRONG","WEAK"],"files":[{"path":"/Users/ghost/Dev/nexus/engine/cross_domain/v1_P106_P112.jsonl","basename":"v1_P106_P112.jsonl","line_count":21},{"path":"/Users/ghost/Dev/nexus/engine/cross_domain/v1_P81_P89.jsonl","basename":"v1_P81_P89.jsonl","line_count":27},{"path":"/Users/ghost/Dev/nexus/engine/cross_domain/v1_P90_P96.jsonl","basename":"v1_P90_P96.jsonl","line_count":21},{"path":"/Users/ghost/Dev/nexus/engine/cross_domain/v1_P97_P105.jsonl","basename":"v1_P97_P105.jsonl","line_count":27}],"n6_match_distribution":{"EXACT":41,"STRONG":46,"WEAK":9,"OTHER":0,"total":96},"phase_coverage":{"P1":0,"P2":0,"P3":0,"P4":0,"P5":0,"P6":0,"P7":0,"P8":0,"P9":0,"P10":0,"P11":0,"P12":0,"P13":0,"P14":0,"P15":0,"P16":0,"P17":0,"P18":0,"P19":0,"P20":0,"P21":0,"P22":0,"P23":0,"P24":0,"P25":0,"P26":0,"P27":0,"P28":0,"P29":0,"P30":0,"P31":0,"P32":0,"P33":0,"P34":0,"P35":0,"P36":0,"P37":0,"P38":0,"P39":0,"P40":0,"P41":0,"P42":0,"P43":0,"P44":0,"P45":0,"P46":0,"P47":0,"P48":0,"P49":0,"P50":0,"P51":0,"P52":0,"P53":0,"P54":0,"P55":0,"P56":0,"P57":0,"P58":0,"P59":0,"P60":0,"P61":0,"P62":0,"P63":0,"P64":0,"P65":0,"P66":0,"P67":0,"P68":0,"P69":0,"P70":0,"P71":0,"P72":0,"P73":0,"P74":0,"P75":0,"P76":0,"P77":0,"P78":0,"P79":0,"P80":0,"P81":3,"P82":3,"P83":3,"P84":3,"P85":3,"P86":3,"P87":3,"P88":3,"P89":3,"P90":3,"P91":3,"P92":3,"P93":3,"P94":3,"P95":3,"P96":3,"P97":3,"P98":3,"P99":3,"P100":3,"P101":3,"P102":3,"P103":3,"P104":3,"P105":3,"P106":3,"P107":3,"P108":3,"P109":3,"P110":3,"P111":3,"P112":3},"phase_covered":["P81","P82","P83","P84","P85","P86","P87","P88","P89","P90","P91","P92","P93","P94","P95","P96","P97","P98","P99","P100","P101","P102","P103","P104","P105","P106","P107","P108","P109","P110","P111","P112"],"phase_gaps":["P1","P2","P3","P4","P5","P6","P7","P8","P9","P10","P11","P12","P13","P14","P15","P16","P17","P18","P19","P20","P21","P22","P23","P24","P25","P26","P27","P28","P29","P30","P31","P32","P33","P34","P35","P36","P37","P38","P39","P40","P41","P42","P43","P44","P45","P46","P47","P48","P49","P50","P51","P52","P53","P54","P55","P56","P57","P58","P59","P60","P61","P62","P63","P64","P65","P66","P67","P68","P69","P70","P71","P72","P73","P74","P75","P76","P77","P78","P79","P80"],"phase_distinct_count":32,"top_invariants":[{"key":"tau=4 (4 macrostate regimes)","count":2},{"key":"tau=4 (4 pipeline stages)","count":2},{"key":"mu (Mobius squarefree cancellation)","count":2},{"key":"sigma=12 (12 as total power budget across divisor channels)","count":1},{"key":"sigma=12 (12 as conserved flux quantum count)","count":1},{"key":"sigma=12 (12 as census total over divisor-class strata)","count":1},{"key":"tau=4 (4 divisors ~ 4 resolution octaves)","count":1},{"key":"tau=4 (log2(4)=2 bits ~ Shannon entropy ceiling)","count":1},{"key":"tau=4 (4-way set associativity ~ 4 divisor slots)","count":1},{"key":"n=6 (6-vertex relation ~ 6-node graph canonical)","count":1}],"top_source_domains":[{"key":"plasma","count":18},{"key":"consciousness","count":12},{"key":"breakthrough","count":12},{"key":"compiler","count":9},{"key":"thermodynamics","count":9},{"key":"singularity","count":9},{"key":"BT","count":6},{"key":"sigma","count":3},{"key":"tau","count":3},{"key":"relation","count":3}],"top_target_domains":[{"key":"ocean","count":3},{"key":"traffic","count":3},{"key":"immune","count":3},{"key":"swarm","count":3},{"key":"cortex","count":3},{"key":"market","count":3},{"key":"evolution","count":3},{"key":"ecology","count":3},{"key":"language","count":3},{"key":"field","count":3}],"pair_id_distinct":96,"pair_id_duplicates":[],"fail_detail":[]}
