{
  "dest": "alm",
  "round": "r12",
  "ts": "2026-04-20T16:58:28Z",
  "source": "primary",
  "eigen_count": 8,
  "template_count": 16,
  "max_cosine": 0.998046,
  "max_cosine_pair": {
    "eigen_i": 0,
    "template_id": "hexad_c",
    "template_family": "Hexad"
  },
  "top3_pairs": [
    {"eigen_i": 0, "template_id": "hexad_c", "template_family": "Hexad", "cosine": 0.998046},
    {"eigen_i": 1, "template_id": "hexad_d", "template_family": "Hexad", "cosine": 0.994841},
    {"eigen_i": 2, "template_id": "hexad_w", "template_family": "Hexad", "cosine": 0.994457}
  ],
  "top3_cosine_sum": 2.98734,
  "family_coverage": {
    "Hexad": 6,
    "Law": 3,
    "Phi": 3,
    "SelfRef": 4
  },
  "gate": {
    "max_cosine_min": 0.5,
    "top3_cosine_sum_min": 1.2
  },
  "verdict": "PASS",
  "reason": "max_cos=0.998046 > 0.5 AND top3_sum=2.98734 > 1.2",
  "exit_code": 0
}
