{
  "schema": "hire_sim_regression/v1",
  "ts_utc": "2026-04-17T10:45:00Z",
  "source_eval": "training/deploy/hire_sim_lenient_20260417_015253.json",
  "issue": "Z_lenient_judge_raw_endpoint regression vs baseline",
  "measured": {
    "completion_rate": 0.4333,
    "avg_score": 0.5667
  },
  "baseline": {
    "completion_rate": 0.5333,
    "avg_score": 0.8111
  },
  "pathc": {
    "completion_rate": 0.8667,
    "avg_score": 0.9444
  },
  "delta_vs_baseline": -0.1,
  "delta_vs_pathc": -0.4334,
  "gates": {
    "alm_0.85": false,
    "clm_0.80": false,
    "z_0.75": false,
    "verdict": "BLOCKED_<0.60"
  },
  "hypothesis": [
    "Endpoint itfl66q4z768kh or localhost:18282 served stale/wrong model (avg_len 127 for CD01/CD03 suggests truncation)",
    "Domain 'schedule' 0/5 completion — numeric_tolerance rule likely catches model refusal patterns",
    "Code tasks 'extra_fail(no code / structured steps)' — model not emitting code blocks"
  ],
  "next_action": "diagnose endpoint response quality — compare serving config vs training/deploy/hire_sim_config at invocation time; this is BLOCKED<0.60 — do not advance TSRV-P4-2 gate until resolved"
}