{
  "schema": "zeta_ab_harness/v1",
  "date": "2026-04-16",
  "task": "TSRV-P5-3 v2.0_RC criterion 3 — Zeta AI Likert comparison harness",
  "context": {
    "criterion": "ALM/CLM Likert mean > Zeta AI (Scatter Lab Zeta chat service)",
    "thresholds": {
      "alm": { "diff_min": 0.25, "p_max": 0.05, "n_min": 30 },
      "clm": { "diff_min": 0.40, "p_max": 0.01, "n_min": 30 }
    },
    "test_type": "Mann-Whitney U (non-parametric, ordinal Likert 5-point)",
    "zeta_policy": "No live API calls — ethics/free-tier. Zeta responses collected offline into CSV, loaded blind."
  },
  "artifacts": {
    "prompts":  "anima-agent/zeta_ab_prompts.jsonl",
    "runner":   "anima-agent/zeta_ab_runner.hexa",
    "blind_ui": "anima-agent/zeta_ab_blind_ui.hexa",
    "stats":    "anima-agent/zeta_ab_stats.hexa"
  },
  "prompt_set": {
    "total": 38,
    "categories": {
      "casual_chat":     8,
      "empathy":         8,
      "problem_solving": 8,
      "creative":        6,
      "korean_specific": 8
    },
    "language": "ko"
  },
  "pipeline": {
    "stage_1_runner": {
      "input":  ["anima-agent/zeta_ab_prompts.jsonl", "zeta_responses.csv (user-collected)"],
      "output": "shared/state/zeta_ab_pairs_{ts}.jsonl",
      "cli":    "$HEXA anima-agent/zeta_ab_runner.hexa run <provider> <zeta_csv>",
      "mock":   "$HEXA anima-agent/zeta_ab_runner.hexa mock"
    },
    "stage_2_blind_ui": {
      "input":  "shared/state/zeta_ab_pairs_{ts}.jsonl",
      "output": "shared/state/zeta_ab_responses_{ts}.jsonl",
      "cli":    "$HEXA anima-agent/zeta_ab_blind_ui.hexa run <pair_file>",
      "simulate": "$HEXA anima-agent/zeta_ab_blind_ui.hexa simulate <pair_file> <n>",
      "blinding": "per-pair coin flip (LCG seeded by wall clock) decides if column A = anima",
      "order": "Fisher-Yates shuffle over pair indices"
    },
    "stage_3_stats": {
      "input":  "shared/state/zeta_ab_responses_{ts}.jsonl",
      "output": "stdout report + LikertStats struct",
      "cli":    "$HEXA anima-agent/zeta_ab_stats.hexa analyze <responses_jsonl>",
      "mock":   "$HEXA anima-agent/zeta_ab_stats.hexa mock",
      "algorithm": "Mann-Whitney U with tie correction + continuity correction + normal approx p-value"
    }
  },
  "mock_dry_run": {
    "mock_built_in_stats": {
      "description": "30 anima scores (~mean 4.23) vs 30 zeta (~mean 3.40), baked into zeta_ab_stats.hexa",
      "n_total": 60,
      "mean_anima": 4.23333,
      "mean_zeta": 3.4,
      "diff": 0.83333,
      "u_statistic": 735.0,
      "z_score": 4.58981,
      "p_value_one_sided": 0.0,
      "verdict_alm": "PASS",
      "verdict_clm": "PASS"
    },
    "full_pipeline_e2e": {
      "description": "runner mock → blind_ui simulate 30 → stats analyze",
      "n_total": 60,
      "mean_anima": 4.4,
      "mean_zeta": 3.03333,
      "diff": 1.36667,
      "u_statistic": 798.0,
      "z_score": 5.35354,
      "p_value_one_sided": 0.0,
      "verdict_alm": "PASS",
      "verdict_clm": "PASS"
    },
    "edge_case_insufficient": {
      "description": "10-pair simulate (n<30)",
      "n_total": 20,
      "diff": 1.3,
      "p_value_one_sided": 0.00144,
      "verdict_alm": "INSUFFICIENT",
      "verdict_clm": "INSUFFICIENT"
    },
    "edge_case_fail": {
      "description": "30 synthetic pairs with anima<zeta",
      "n_total": 60,
      "diff": -0.43333,
      "p_value_one_sided": 0.9974,
      "verdict_alm": "FAIL",
      "verdict_clm": "FAIL"
    }
  },
  "hexa_quirks_handled": [
    "&& / || are eager (no short-circuit) — split guards into nested if",
    "arrays are pass-by-value — index assignment arr[i]=v works on mutable locals only",
    "no .set() method on arrays — use direct index assignment",
    "no dual-return — pack parallel arrays into single flat array with sentinel",
    "read_file returns Error type for missing paths — probe via split"
  ],
  "next_steps_for_real_eval": [
    "Collect real Zeta AI responses offline to zeta_responses.csv (id,response)",
    "Run: $HEXA anima-agent/zeta_ab_runner.hexa run animalm zeta_responses.csv",
    "Run: $HEXA anima-agent/zeta_ab_blind_ui.hexa run shared/state/zeta_ab_pairs_<ts>.jsonl",
    "Collect ≥30 human Likert ratings (each rating covers one pair → 2 scores, so ≥30 pair ratings total)",
    "Run: $HEXA anima-agent/zeta_ab_stats.hexa analyze shared/state/zeta_ab_responses_<ts>.jsonl",
    "Record verdict in shared/state/zeta_ab_v2_rc_gate_<date>.json",
    "Gate passes iff ALM verdict=PASS (criterion 3 for v2.0_RC)"
  ],
  "guardrails": {
    "l0_freeze": "all new files are anima-agent-scope; no anima-core touching",
    "hexa_only": "no .py/.rs/.sh new files; no Python fallback",
    "no_zeta_api": "live Zeta calls prohibited — CSV ingestion only",
    "worktree_isolation": "built in agent-a7b1271a worktree, clean merge path"
  },
  "gate_status": "HARNESS_READY — real user evaluation blocked on Zeta response collection + human raters"
}
