{
  "absorbed_from": "/Users/ghost/Dev/ready/redo/nexus6/src/telescope/lenses/solar_efficiency_lens.rs",
  "original_path": "nexus6/src/telescope/lenses/solar_efficiency_lens.rs",
  "value_grade": "high",
  "n6_score": 0.0,
  "n6_matches": [],
  "consensus": [],
  "timestamp": "2026-04-04T17:07:36.867494",
  "content_preview": "use std::collections::HashMap;\n\nuse crate::telescope::lens_trait::{Lens, LensResult};\nuse crate::telescope::shared_data::{SharedData, mean_var, shannon_entropy};\n\n/// n=6 solar constants (BT-30, BT-63)\nconst SIGMA: f64 = 12.0;\nconst SIGMA_SQ: f64 = 144.0;  // σ² = 144 cells\nconst SOPFR: f64 = 5.0;\nconst N: f64 = 6.0;\nconst TAU: f64 = 4.0;\nconst PHI: f64 = 2.0;\nconst J2: f64 = 24.0;\n\n/// Shockley-Queisser bandgap = 4/3 eV (BT-30, BT-111)\nconst SQ_BANDGAP: f64 = 4.0 / 3.0;\n\n/// Solar panel cell co"
}