{
  "absorbed_from": "/Users/ghost/Dev/ready/redo/TECS-L/texas_quantum.py",
  "original_path": "TECS-L/texas_quantum.py",
  "value_grade": "critical",
  "n6_score": 41.66666666666667,
  "n6_matches": [],
  "consensus": [
    {
      "pattern": "",
      "lenses": 0,
      "score": 0.0,
      "level": "Candidate"
    },
    {
      "pattern": "",
      "lenses": 0,
      "score": 0.0,
      "level": "Candidate"
    }
  ],
  "timestamp": "2026-04-04T17:07:36.135283",
  "content_preview": "#!/usr/bin/env python3\n\"\"\"Texas Sharpshooter Test — Quantum/Physics Discovery Exclusive\n\nScans the parameter space of each discovery to calculate chance hit probability (p-value),\nand applies Bonferroni correction for multiple comparison problem.\n\nUsage:\n  python3 texas_quantum.py                        # Full test\n  python3 texas_quantum.py --discovery \"1/alpha\"   # Specific discovery only\n  python3 texas_quantum.py --monte-carlo 100000    # Monte Carlo iterations\n\"\"\"\n\nimport argparse\nimport it"
}