{
  "absorbed_from": "/Users/ghost/Dev/ready/redo/TECS-L/scripts/convert_mistral_to_golden_moa.py",
  "original_path": "TECS-L/scripts/convert_mistral_to_golden_moa.py",
  "value_grade": "critical",
  "n6_score": 37.5,
  "n6_matches": [],
  "consensus": [
    {
      "pattern": "",
      "lenses": 0,
      "score": 0.0,
      "level": "Candidate"
    },
    {
      "pattern": "",
      "lenses": 0,
      "score": 0.0,
      "level": "Candidate"
    },
    {
      "pattern": "",
      "lenses": 0,
      "score": 0.0,
      "level": "Candidate"
    }
  ],
  "timestamp": "2026-04-04T17:07:36.123044",
  "content_preview": "#!/usr/bin/env python3\n\"\"\"Mistral 7B → Golden MoA Converter\n\nSplits Dense FFN into N Experts and equips with Boltzmann router (T=e).\nSavant tuning: Domain specialization per Expert → Target Savant Index > 3.\n\nConversion strategy:\n  1. Attention layers: Preserve as-is\n  2. FFN (gate_proj + up_proj + down_proj): Split into N equal parts to create Experts\n  3. Add Boltzmann router (T=e, 70% active)\n  4. Weight copying: Split original FFN columns/rows by N\n\"\"\"\n\nimport argparse\nimport json\nimport mat"
}